[
  {
    "title": "Evanescence - Fallen (Audio CD) - $5.29 at Amazon",
    "url": "https://slickdeals.net/f/19618434-evanescence-fallen-audio-cd-5-29-at-amazon?utm_source=rss&utm_content=ht&utm_medium=RSS2",
    "source": "Slickdeals Hot",
    "discount": 50,
    "original": null,
    "sale": null,
    "category": "general",
    "glitch": false,
    "hot": true,
    "found_at": "2026-06-12T06:36:55.404223"
  },
  {
    "title": "G Gradual Women's High-Waisted Ankle Pants w/ Drawstring (Various) $14.99 + Free Shipping w/ Prime or on $35+",
    "url": "https://slickdeals.net/f/19618875-g-gradual-women-s-high-waisted-ankle-pants-w-drawstring-various-14-99-free-shipping-w-prime-or-on-35?utm_source=rss&utm_content=ht&utm_medium=RSS2",
    "source": "Slickdeals Hot",
    "discount": 50,
    "original": null,
    "sale": null,
    "category": "clothing",
    "glitch": false,
    "hot": true,
    "found_at": "2026-06-12T06:36:55.404623"
  },
  {
    "title": "ONLYCARE Ankle Ice Pack Wrap w/ Gel for Hot & Cold Therapy $9.99 + Free Shipping w/ Prime or on $35+",
    "url": "https://slickdeals.net/f/19615425-onlycare-ankle-ice-pack-wrap-w-gel-for-hot-cold-therapy-9-99-free-shipping-w-prime-or-on-35?utm_source=rss&utm_content=ht&utm_medium=RSS2",
    "source": "Slickdeals Hot",
    "discount": 50,
    "original": null,
    "sale": null,
    "category": "general",
    "glitch": false,
    "hot": true,
    "found_at": "2026-06-12T01:43:34.111413"
  },
  {
    "title": "2-Pack SupBri 12 Artificial Silk Pansies Flowers w/ Hanging Baskets $22.49 + Free Shipping w/ Prime or on $35+",
    "url": "https://slickdeals.net/f/19619439-2-pack-supbri-12-artificial-silk-pansies-flowers-w-hanging-baskets-22-49-free-shipping-w-prime-or-on-35?utm_source=rss&utm_content=ht&utm_medium=RSS2",
    "source": "Slickdeals Hot",
    "discount": 50,
    "original": null,
    "sale": null,
    "category": "general",
    "glitch": false,
    "hot": true,
    "found_at": "2026-06-12T01:43:34.112252"
  },
  {
    "title": "3-Count QALLY Women's Polarized UV400 Fashion Sunglasses (Various) from $9.49 ($3.16 each) + Free Shipping w/ Prime or on $35+",
    "url": "https://slickdeals.net/f/19619424-3-count-qally-women-s-polarized-uv400-fashion-sunglasses-various-from-9-49-3-16-each-free-shipping-w-prime-or-on-35?utm_source=rss&utm_content=ht&utm_medium=RSS2",
    "source": "Slickdeals Hot",
    "discount": 50,
    "original": null,
    "sale": null,
    "category": "clothing",
    "glitch": false,
    "hot": true,
    "found_at": "2026-06-11T23:25:01.648689"
  },
  {
    "title": "Lowe\u2019s Tarp Sale! Up to 70% Off + Extra 30% Off 3+ $21.02",
    "url": "https://slickdeals.net/f/19618044-lowe-s-tarp-sale-up-to-70-off-extra-30-off-3-21-02?utm_source=rss&utm_content=ht&utm_medium=RSS2",
    "source": "Slickdeals Hot",
    "discount": 70,
    "original": null,
    "sale": null,
    "category": "general",
    "glitch": false,
    "hot": true,
    "found_at": "2026-06-11T21:58:06.925542"
  },
  {
    "title": "BOOJO Men's UPF 50+ Sun Protection Long Sleeve Performance Shirts (L or XL, Black or White) $4.99 + Free Shipping w/ Prime or on $35+",
    "url": "https://slickdeals.net/f/19618581-boojo-men-s-upf-50-sun-protection-long-sleeve-performance-shirts-l-or-xl-black-or-white-4-99-free-shipping-w-prime-or-on-35?utm_source=rss&utm_content=ht&utm_medium=RSS2",
    "source": "Slickdeals Hot",
    "discount": 50,
    "original": null,
    "sale": null,
    "category": "clothing",
    "glitch": false,
    "hot": true,
    "found_at": "2026-06-11T21:58:06.926161"
  },
  {
    "title": "$4.99: LEGO Marvel Super Heroes @ PlayStation Store",
    "url": "https://slickdeals.net/f/19615602-4-99-lego-marvel-super-heroes-playstation-store?utm_source=rss&utm_content=ht&utm_medium=RSS2",
    "source": "Slickdeals Hot",
    "discount": 75,
    "original": null,
    "sale": null,
    "category": "gaming",
    "glitch": false,
    "hot": true,
    "found_at": "2026-06-11T21:58:06.926193"
  },
  {
    "title": "Newegg Summer Bonanza Game On Sale: Up to 73% off + free shipping",
    "url": "https://www.dealnews.com/Newegg-Summer-Bonanza-Game-On-Sale-Up-to-73-off-free-shipping/21840062.html?iref=rss-c142",
    "source": "DealNews Electronics",
    "discount": 73,
    "original": null,
    "sale": null,
    "category": "general",
    "glitch": false,
    "hot": true,
    "found_at": "2026-06-11T21:58:07.755447"
  },
  {
    "title": "Newegg Summer Bonanza : Up to 52% off  + free shipping on many items",
    "url": "https://www.dealnews.com/Newegg-Summer-Bonanza-Up-to-52-off-free-shipping-on-many-items/21840061.html?iref=rss-c142",
    "source": "DealNews Electronics",
    "discount": 52,
    "original": null,
    "sale": null,
    "category": "general",
    "glitch": false,
    "hot": true,
    "found_at": "2026-06-11T21:58:07.755499"
  },
  {
    "title": "Newegg Shell Shocker Deals:  Up to 54% off  + free shipping",
    "url": "https://www.dealnews.com/Newegg-Shell-Shocker-Deals-Up-to-54-off-free-shipping/21840053.html?iref=rss-c142",
    "source": "DealNews Electronics",
    "discount": 54,
    "original": null,
    "sale": null,
    "category": "general",
    "glitch": false,
    "hot": true,
    "found_at": "2026-06-11T21:58:07.755615"
  },
  {
    "title": "Best Buy Deals That Bring the Whoa : Up to 80% off +  free shipping",
    "url": "https://www.dealnews.com/Best-Buy-Deals-That-Bring-the-Whoa-Up-to-80-off-free-shipping/21840046.html?iref=rss-c142",
    "source": "DealNews Electronics",
    "discount": 80,
    "original": null,
    "sale": null,
    "category": "general",
    "glitch": false,
    "hot": false,
    "found_at": "2026-06-11T19:31:37.201274"
  },
  {
    "title": "eBay Father's Day Tech Deals: Up to 50% off + extra 20% off + free shipping",
    "url": "https://www.dealnews.com/eBay-Fathers-Day-Tech-Deals-Up-to-50-off-extra-20-off-free-shipping/21840026.html?iref=rss-c142",
    "source": "DealNews Electronics",
    "discount": 50,
    "original": null,
    "sale": null,
    "category": "general",
    "glitch": false,
    "hot": true,
    "found_at": "2026-06-11T19:31:37.201463"
  },
  {
    "title": "Barnes & Noble: Select Lionsgate Studio Films (4K UHD / Blu-ray / DVD) 50% Off + Free S&H on $60+",
    "url": "https://slickdeals.net/f/19617192-barnes-noble-50-off-all-lionsgate-films?utm_source=rss&utm_content=fp&utm_medium=RSS2",
    "source": "Slickdeals",
    "discount": 50,
    "original": null,
    "sale": null,
    "category": "general",
    "glitch": false,
    "hot": true,
    "found_at": "2026-06-11T16:34:55.462400"
  },
  {
    "title": "26L GOLF SUPAGS 15.6\" Laptop Backpack (Apricot) $14.99 + Free Shipping w/ Prime or on $35+",
    "url": "https://slickdeals.net/f/19606860-26l-golf-supags-15-6-laptop-backpack-apricot-14-99-free-shipping-w-prime-or-on-35?utm_source=rss&utm_content=ht&utm_medium=RSS2",
    "source": "Slickdeals Hot",
    "discount": 50,
    "original": null,
    "sale": null,
    "category": "electronics",
    "glitch": false,
    "hot": true,
    "found_at": "2026-06-11T16:34:56.234649"
  },
  {
    "title": "PS4/PS5 Mid-Year Digital Games Sale: Dave the Diver $11, Blasphemous $2.50 & Many More",
    "url": "https://slickdeals.net/f/19614486-playstation-digital-game-megathread-blasphemous-2-49-uncharted-the-nathan-drake-collection-6-dave-the-diver-11-more?utm_source=rss&utm_content=fp&utm_medium=RSS2",
    "source": "Slickdeals",
    "discount": 75,
    "original": null,
    "sale": null,
    "category": "gaming",
    "glitch": false,
    "hot": true,
    "found_at": "2026-06-11T12:26:36.103015"
  },
  {
    "title": "Open-Box Apple Deals at Best Buy: Up to 50% off + free shipping",
    "url": "https://www.dealnews.com/Open-Box-Apple-Deals-at-Best-Buy-Up-to-50-off-free-shipping/21839874.html?iref=rss-c142",
    "source": "DealNews Electronics",
    "discount": 50,
    "original": null,
    "sale": null,
    "category": "general",
    "glitch": false,
    "hot": true,
    "found_at": "2026-06-11T12:26:37.340185"
  },
  {
    "title": "Beats Headphones at Best Buy: Up to 55% off + free shipping",
    "url": "https://www.dealnews.com/Beats-Headphones-at-Best-Buy-Up-to-55-off-free-shipping/21839865.html?iref=rss-c142",
    "source": "DealNews Electronics",
    "discount": 55,
    "original": null,
    "sale": null,
    "category": "electronics",
    "glitch": false,
    "hot": true,
    "found_at": "2026-06-11T12:26:37.340225"
  },
  {
    "title": "Heating and Cooling Early Prime Day Deals at Amazon: Up to 70% off + free shipping w/ Prime",
    "url": "https://www.dealnews.com/Heating-and-Cooling-Early-Prime-Day-Deals-at-Amazon-Up-to-70-off-free-shipping-w-Prime/21839937.html?iref=rss-c304",
    "source": "DealNews Sports",
    "discount": 70,
    "original": null,
    "sale": null,
    "category": "general",
    "glitch": false,
    "hot": true,
    "found_at": "2026-06-11T12:26:39.468334"
  },
  {
    "title": "Heating & Cooling Deals at Lowe's  : Up to 52% off   + Free shipping w/ $35",
    "url": "https://www.dealnews.com/Heating-Cooling-Deals-at-Lowes-Up-to-52-off-Free-shipping-w-35/21839924.html?iref=rss-c304",
    "source": "DealNews Sports",
    "discount": 52,
    "original": null,
    "sale": null,
    "category": "general",
    "glitch": false,
    "hot": true,
    "found_at": "2026-06-11T12:26:39.468459"
  },
  {
    "title": "Minecraft Dungeons (PC Digital) $10",
    "url": "https://slickdeals.net/f/19606002-9-99-minecraft-dungeons-ultimate-edition-steam?utm_source=rss&utm_content=fp&utm_medium=RSS2",
    "source": "Slickdeals",
    "discount": 75,
    "original": null,
    "sale": null,
    "category": "general",
    "glitch": false,
    "hot": true,
    "found_at": "2026-06-11T08:20:26.839374"
  },
  {
    "title": "Sinophant Women's High Waisted Leggings (Various Colors / Styles) from $4",
    "url": "https://slickdeals.net/f/19597527-sinophant-high-waisted-leggings-various-colors-capri-full-length-and-cross-waist-from-3-74-free-shipping-w-prime-or-on-35?utm_source=rss&utm_content=fp&utm_medium=RSS2",
    "source": "Slickdeals",
    "discount": 50,
    "original": null,
    "sale": null,
    "category": "general",
    "glitch": false,
    "hot": true,
    "found_at": "2026-06-11T03:28:20.198070"
  },
  {
    "title": "Astronaut Galaxy LED Projector for Kids w/ 8 Colors Nebula & Stars $8",
    "url": "https://slickdeals.net/f/19615620-astronaut-galaxy-led-projector-for-kids-w-8-colors-nebula-stars-7-99-free-shipping-w-prime-or-on-35?utm_source=rss&utm_content=fp&utm_medium=RSS2",
    "source": "Slickdeals",
    "discount": 50,
    "original": null,
    "sale": null,
    "category": "electronics",
    "glitch": false,
    "hot": true,
    "found_at": "2026-06-11T03:28:20.198111"
  },
  {
    "title": "YINEYA Slow Feeder Dog Bowl (Black, Medium)  $3.99 + Free Shipping w/ Prime or on $35+",
    "url": "https://slickdeals.net/f/19615743-yineya-slow-feeder-dog-bowl-black-medium-3-99-free-shipping-w-prime-or-on-35?utm_source=rss&utm_content=ht&utm_medium=RSS2",
    "source": "Slickdeals Hot",
    "discount": 50,
    "original": null,
    "sale": null,
    "category": "general",
    "glitch": false,
    "hot": true,
    "found_at": "2026-06-11T03:28:20.666315"
  },
  {
    "title": "6-Pack Ready To Love Women's 95% Cotton Cheeky Low Rise Hipster Underwear: M $4.24, XS-S, L-XXL $6.49  + Free Shipping w/ Prime or on $35+",
    "url": "https://slickdeals.net/f/19613454-6-pack-ready-to-love-women-s-95-cotton-cheeky-low-rise-hipster-underwear-m-4-24-xs-s-l-xxl-6-49-free-shipping-w-prime-or-on-35?utm_source=rss&utm_content=ht&utm_medium=RSS2",
    "source": "Slickdeals Hot",
    "discount": 50,
    "original": null,
    "sale": null,
    "category": "general",
    "glitch": false,
    "hot": true,
    "found_at": "2026-06-10T22:25:08.279478"
  },
  {
    "title": "Vivohome Register Booster Fan with Smart Control for $34 + free shipping",
    "url": "https://www.dealnews.com/Vivohome-Register-Booster-Fan-with-Smart-Control-for-34-free-shipping/21839792.html?iref=rss-c304",
    "source": "DealNews Sports",
    "discount": 50,
    "original": null,
    "sale": null,
    "category": "general",
    "glitch": false,
    "hot": true,
    "found_at": "2026-06-10T22:25:11.186481"
  },
  {
    "title": "Arc'teryx Apparel: Women's Atom SV Insulated Jacket (Nightscape, Limited Sizes) $149.85 & More + Free S&H",
    "url": "https://slickdeals.net/f/19614222-up-to-50-off-arc-teryx-deals-at-rei-limited-sizes?utm_source=rss&utm_content=fp&utm_medium=RSS2",
    "source": "Slickdeals",
    "discount": 50,
    "original": null,
    "sale": null,
    "category": "clothing",
    "glitch": false,
    "hot": true,
    "found_at": "2026-06-10T20:23:13.754292"
  },
  {
    "title": "MAELREG Men's Dry Fit Short Sleeve Performance Polo Shirt (Various) $9.85",
    "url": "https://slickdeals.net/f/19599216-maelreg-men-s-dry-fit-short-sleeve-print-performance-moisture-wicking-polo-shirt-various-12-97-free-shipping-w-prime-or-on-35?utm_source=rss&utm_content=fp&utm_medium=RSS2",
    "source": "Slickdeals",
    "discount": 50,
    "original": null,
    "sale": null,
    "category": "clothing",
    "glitch": false,
    "hot": true,
    "found_at": "2026-06-10T17:54:44.302609"
  },
  {
    "title": "XXXFLOWER 3 Bulb Vase Plant Terrarium w/ Wooden Stand (3 Colors) $6.95",
    "url": "https://slickdeals.net/f/19611759-xxxflower-3-bulb-vase-plant-terrarium-w-wooden-stand-various-6-93-free-shipping-w-prime-or-on-35?utm_source=rss&utm_content=fp&utm_medium=RSS2",
    "source": "Slickdeals",
    "discount": 50,
    "original": null,
    "sale": null,
    "category": "general",
    "glitch": false,
    "hot": true,
    "found_at": "2026-06-10T17:54:44.303044"
  },
  {
    "title": "Up to 50% Off Arc'teryx Deals at REI (Limited Sizes)",
    "url": "https://slickdeals.net/f/19614222-up-to-50-off-arc-teryx-deals-at-rei-limited-sizes?utm_source=rss&utm_content=ht&utm_medium=RSS2",
    "source": "Slickdeals Hot",
    "discount": 50,
    "original": null,
    "sale": null,
    "category": "general",
    "glitch": false,
    "hot": true,
    "found_at": "2026-06-10T17:54:45.032039"
  },
  {
    "title": "VIPOutlet Clearance Sale at eBay: Up to 90% off + Extra 8% off + free shipping",
    "url": "https://www.dealnews.com/VIPOutlet-Clearance-Sale-at-eBay-Up-to-90-off-Extra-8-off-free-shipping/21839717.html?iref=rss-c142",
    "source": "DealNews Electronics",
    "discount": 90,
    "original": null,
    "sale": null,
    "category": "general",
    "glitch": false,
    "hot": false,
    "found_at": "2026-06-10T17:54:45.631448"
  },
  {
    "title": "Prime Members: 360-Ct LitBear Day & Night Acne Pimple Patches $4.05 w/ S&S + Free S&H",
    "url": "https://slickdeals.net/f/19610643-prime-members-360-count-litbear-day-night-acne-pimple-patches-4-04-w-s-s-free-shipping?utm_source=rss&utm_content=fp&utm_medium=RSS2",
    "source": "Slickdeals",
    "discount": 50,
    "original": null,
    "sale": null,
    "category": "general",
    "glitch": false,
    "hot": true,
    "found_at": "2026-06-10T14:34:09.096882"
  },
  {
    "title": "Oakley Men's Bathroom Sink Backpack (Black) $87.50 + Free S&H",
    "url": "https://slickdeals.net/f/19607451-87-50-oakley-men-s-bathroom-sink-stealth-black-one-size?utm_source=rss&utm_content=fp&utm_medium=RSS2",
    "source": "Slickdeals",
    "discount": 50,
    "original": null,
    "sale": null,
    "category": "general",
    "glitch": false,
    "hot": true,
    "found_at": "2026-06-10T14:34:09.097417"
  },
  {
    "title": "LOOKBOHO Women's Floral V-Neck 3/4 Sleeve Blouse Shirt (2 Colors) $6",
    "url": "https://slickdeals.net/f/19610409-lookboho-women-s-floral-v-neck-3-4-sleeve-blouse-shirt-2-colors-5-99-free-shipping-w-prime-or-on-35?utm_source=rss&utm_content=fp&utm_medium=RSS2",
    "source": "Slickdeals",
    "discount": 50,
    "original": null,
    "sale": null,
    "category": "clothing",
    "glitch": false,
    "hot": true,
    "found_at": "2026-06-10T14:34:09.097754"
  },
  {
    "title": "4\"x6\" Phomemo PM64D Wireless Thermal Label Printer w/ Touch Screen $59.99 + Free Shipping w/ Prime or on $35+",
    "url": "https://slickdeals.net/f/19611291-4-x6-phomemo-pm64d-wireless-thermal-label-printer-w-touch-screen-59-99-free-shipping-w-prime-or-on-35?utm_source=rss&utm_content=ht&utm_medium=RSS2",
    "source": "Slickdeals Hot",
    "discount": 58,
    "original": null,
    "sale": null,
    "category": "electronics",
    "glitch": false,
    "hot": true,
    "found_at": "2026-06-10T14:34:09.931126"
  },
  {
    "title": "Refurb Dyson Outlet Appliance Deals at eBay: Up to 70% off + Extra 20% off + free shipping",
    "url": "https://www.dealnews.com/Refurb-Dyson-Outlet-Appliance-Deals-at-eBay-Up-to-70-off-Extra-20-off-free-shipping/21839620.html?iref=rss-c304",
    "source": "DealNews Sports",
    "discount": 70,
    "original": null,
    "sale": null,
    "category": "flipping",
    "glitch": false,
    "hot": true,
    "found_at": "2026-06-10T14:34:12.968704"
  },
  {
    "title": "Capture the Moment Camera Deals at Woot:  Up to 77% off + free shipping w/ Prime",
    "url": "https://www.dealnews.com/Capture-the-Moment-Camera-Deals-at-Woot-Up-to-77-off-free-shipping-w-Prime/21839508.html?iref=rss-c142",
    "source": "DealNews Electronics",
    "discount": 77,
    "original": null,
    "sale": null,
    "category": "flipping",
    "glitch": false,
    "hot": true,
    "found_at": "2026-06-10T11:07:53.135127"
  },
  {
    "title": "5' Firsting 3-in-1 Travel Charging Cable w/ Apple Watch Charger (Lightning & USB-C, Purple/Black) $4.99 + Free Shipping w/ Prime or on $35+",
    "url": "https://slickdeals.net/f/19609848-5-firsting-3-in-1-travel-charging-cable-w-apple-watch-charger-lightning-usb-c-purple-black-4-99-free-shipping-w-prime-or-on-35?utm_source=rss&utm_content=ht&utm_medium=RSS2",
    "source": "Slickdeals Hot",
    "discount": 50,
    "original": null,
    "sale": null,
    "category": "general",
    "glitch": false,
    "hot": true,
    "found_at": "2026-06-10T07:05:34.095528"
  },
  {
    "title": "$19.79: Returnal @ Steam",
    "url": "https://slickdeals.net/f/19607397-19-79-returnal-steam?utm_source=rss&utm_content=ht&utm_medium=RSS2",
    "source": "Slickdeals Hot",
    "discount": 67,
    "original": null,
    "sale": null,
    "category": "general",
    "glitch": false,
    "hot": true,
    "found_at": "2026-06-10T07:05:34.095986"
  },
  {
    "title": "OtterBox & more at Woot: Up to 95% off + free shipping w/ Prime",
    "url": "https://www.dealnews.com/Otter-Box-more-at-Woot-Up-to-95-off-free-shipping-w-Prime/21839479.html?iref=rss-c142",
    "source": "DealNews Electronics",
    "discount": 95,
    "original": null,
    "sale": null,
    "category": "general",
    "glitch": false,
    "hot": false,
    "found_at": "2026-06-10T07:05:34.699418"
  }
]